{
    "f#": "0",
    "g": "1",
    "g#": "2",
    "a": "3",
    "a#": "4",
    "b": "5",
    "c1": "6",
    "c1#": "7",
    "d1": "8",
    "d1#": "9",
    "e1": "10",
    "f1": "11",
    "f1#": "12",
    "g1": "13",
    "g1#": "14",
    "a1": "15",
    "a1#": "16",
    "b1": "17",
    "c2": "18",
    "c2#": "19",
    "d2": "20",
    "d2#": "21",
    "e2": "22",
    "f2": "23",
    "f2#": "24",
    "F4#": "0",
    "G4": "1",
    "G#4": "2",
    "A4": "3",
    "A#4": "4",
    "B4": "5",
    "C5": "6",
    "C#5": "7",
    "D5": "8",
    "D#5": "9",
    "E5": "10",
    "F5": "11",
    "F#5": "12",
    "G5": "13",
    "G#5": "14",
    "A5": "15",
    "A#5": "16",
    "B5": "17",
    "C6": "18",
    "C#6": "19",
    "D6": "20",
    "D#6": "21",
    "E6": "22",
    "F6": "23",
    "F#6": "24"
}